{"Dependencies": [], "FileLength": 4085061, "HasInstallScript": false, "Id": 2225497, "InstallMetadata": null, "Modules": [{"Foldername": "meta-inf", "Fingerprint": 2464251221}, {"Foldername": "com", "Fingerprint": 4018149089}, {"Foldername": "chisel_compile_at.cfg", "Fingerprint": 2885370819}, {"Foldername": "mcmod.info", "Fingerprint": 3708325806}, {"Foldername": "license", "Fingerprint": 3548817399}, {"Foldername": "pack.mcmeta", "Fingerprint": 4223423444}, {"Foldername": "assets", "Fingerprint": 2953109170}], "GameVersionDateReleased": "2014-06-16T00:00:00Z", "__comment": "Deprecated! [Served by AWS Lambda]", "AlternateFileId": 2225498, "FileName": "Chisel2-2.3.5.31.jar", "GameVersion": ["1.7.10"], "ReleaseType": 1, "DisplayName": "Chisel 2 - 2.3.5", "PackageFingerprint": 135502463, "_Project": {"PackageType": "Mod", "Path": "mods"}, "IsAlternate": false, "FileDate": "2015-01-26T01:16:07.67Z", "ServerPackFileId": null, "IsAvailable": false, "GameVersionFlavor": null, "DownloadURL": "https://edge.forgecdn.net/files/2225/497/Chisel2-2.3.5.31.jar", "FileStatus": 8, "FileNameOnDisk": "Chisel2-2.3.5.31.jar"}