{"Dependencies": [], "FileLength": 373947, "HasInstallScript": false, "Id": 2237491, "InstallMetadata": null, "Modules": [{"Foldername": "meta-inf", "Fingerprint": 2464251221}, {"Foldername": "baubles", "Fingerprint": 4156763752}, {"Foldername": "com", "Fingerprint": 670998388}, {"Foldername": "latmod", "Fingerprint": 430199485}, {"Foldername": "mcp", "Fingerprint": 342744109}, {"Foldername": "mcmod.info", "Fingerprint": 2147808553}, {"Foldername": "assets", "Fingerprint": 2369455451}], "GameVersionDateReleased": "2014-06-16T00:00:00Z", "__comment": "Deprecated! [Served by AWS Lambda]", "AlternateFileId": 0, "FileName": "LatCoreMC-1.7.10-1.6.9.4.jar", "GameVersion": ["1.7.10"], "ReleaseType": 1, "DisplayName": "LatCoreMC-1.7.10-1.6.9.4.jar", "PackageFingerprint": 2004304780, "_Project": {"PackageType": "Mod", "Path": "mods"}, "IsAlternate": false, "FileDate": "2015-05-09T21:11:43.997Z", "ServerPackFileId": null, "IsAvailable": true, "GameVersionFlavor": null, "DownloadURL": "https://edge.forgecdn.net/files/2237/491/LatCoreMC-1.7.10-1.6.9.4.jar", "FileStatus": 4, "FileNameOnDisk": "LatCoreMC-1.7.10-1.6.9.4.jar"}