{"Dependencies": [{"Type": 2, "AddonId": 69162}], "FileLength": 255065, "HasInstallScript": false, "Id": 2261835, "InstallMetadata": null, "Modules": [{"Foldername": "meta-inf", "Fingerprint": 2464251221}, {"Foldername": "cofh", "Fingerprint": 4066051370}, {"Foldername": "org", "Fingerprint": 381296295}, {"Foldername": "logo.png", "Fingerprint": 4276928964}, {"Foldername": "logo.xcf", "Fingerprint": 3920110704}, {"Foldername": "mcmod.info", "Fingerprint": 1889139304}, {"Foldername": "assets", "Fingerprint": 1855969668}], "GameVersionDateReleased": "2014-06-16T00:00:00Z", "__comment": "Deprecated! [Served by AWS Lambda]", "AlternateFileId": 0, "FileName": "Electrometrics-1.7.10-0.1.2.jar", "GameVersion": ["1.7.10"], "ReleaseType": 2, "DisplayName": "Electrometrics-1.7.10-0.1.2.jar", "PackageFingerprint": 946796654, "_Project": {"PackageType": "Mod", "Path": "mods"}, "IsAlternate": false, "FileDate": "2015-10-10T22:03:57.21Z", "ServerPackFileId": null, "IsAvailable": true, "GameVersionFlavor": null, "DownloadURL": "https://edge.forgecdn.net/files/2261/835/Electrometrics-1.7.10-0.1.2.jar", "FileStatus": 4, "FileNameOnDisk": "Electrometrics-1.7.10-0.1.2.jar"}