{"Dependencies": [], "FileLength": 8972733, "HasInstallScript": false, "Id": 2270968, "InstallMetadata": null, "Modules": [{"Foldername": "META-INF", "Fingerprint": 2464251221}, {"Foldername": "foxz", "Fingerprint": 3701863844}, {"Foldername": "net", "Fingerprint": 985582665}, {"Foldername": "noppes", "Fingerprint": 4114009824}, {"Foldername": "tconstruct", "Fingerprint": 1937906091}, {"Foldername": "mcmod.info", "Fingerprint": 2102252651}, {"Foldername": "assets", "Fingerprint": 2165888837}], "GameVersionDateReleased": "2014-06-16T00:00:00Z", "__comment": "Deprecated! [Served by AWS Lambda]", "AlternateFileId": 0, "FileName": "CustomNPCs_1.7.10d.jar", "GameVersion": ["1.7.10"], "ReleaseType": 1, "DisplayName": "CustomNPCs_1.7.10d.jar", "PackageFingerprint": 3366020412, "_Project": {"PackageType": "Mod", "Path": "mods"}, "IsAlternate": false, "FileDate": "2015-12-15T17:11:14.957Z", "ServerPackFileId": null, "IsAvailable": false, "GameVersionFlavor": null, "DownloadURL": "https://edge.forgecdn.net/files/2270/968/CustomNPCs_1.7.10d.jar", "FileStatus": 8, "FileNameOnDisk": "CustomNPCs_1.7.10d.jar"}