{"Dependencies": [], "FileLength": 266738, "HasInstallScript": false, "Id": 2279518, "InstallMetadata": null, "Modules": [{"Foldername": "META-INF", "Fingerprint": 1432006404}, {"Foldername": "api", "Fingerprint": 3402554236}, {"Foldername": "license-gpl.txt", "Fingerprint": 949489070}, {"Foldername": "license-lgpl.txt", "Fingerprint": 2972570874}, {"Foldername": "license.txt", "Fingerprint": 4265684607}], "GameVersionDateReleased": "2015-12-09T06:00:00Z", "__comment": "Deprecated! [Served by AWS Lambda]", "AlternateFileId": 0, "FileName": "PlayerAPI-1.8.9-1.0.jar", "GameVersion": ["1.8.9"], "ReleaseType": 1, "DisplayName": "Player API version 1.0 for Minecraft 1.8.9", "PackageFingerprint": 2410394713, "_Project": {"PackageType": "Mod", "Path": "mods"}, "IsAlternate": false, "FileDate": "2016-02-01T21:56:36.977Z", "ServerPackFileId": null, "IsAvailable": true, "GameVersionFlavor": null, "DownloadURL": "https://edge.forgecdn.net/files/2279/518/PlayerAPI-1.8.9-1.0.jar", "FileStatus": 4, "FileNameOnDisk": "PlayerAPI-1.8.9-1.0.jar"}