{"Dependencies": [{"Type": 1, "AddonId": 74652}], "FileLength": 192757, "HasInstallScript": false, "Id": 2293330, "InstallMetadata": null, "Modules": [{"Foldername": "alchemycraft2.png", "Fingerprint": 2435015733}, {"Foldername": "assets", "Fingerprint": 2059908982}, {"Foldername": "com", "Fingerprint": 4101392092}, {"Foldername": "mcmod.info", "Fingerprint": 3917382985}, {"Foldername": "META-INF", "Fingerprint": 2464251221}], "GameVersionDateReleased": "2015-12-09T06:00:00Z", "__comment": "Deprecated! [Served by AWS Lambda]", "AlternateFileId": 0, "FileName": "alchemycraft2 v1.3.2.jar", "GameVersion": ["1.8.9"], "ReleaseType": 2, "DisplayName": "alchemycraft2 v1.3.2.jar", "PackageFingerprint": 1623800541, "_Project": {"PackageType": "Mod", "Path": "mods"}, "IsAlternate": false, "FileDate": "2016-04-09T23:37:57.257Z", "ServerPackFileId": null, "IsAvailable": true, "GameVersionFlavor": null, "DownloadURL": "https://edge.forgecdn.net/files/2293/330/alchemycraft2 v1.3.2.jar", "FileStatus": 4, "FileNameOnDisk": "alchemycraft2 v1.3.2.jar"}