{"Dependencies": [{"Type": 3, "AddonId": 74924}], "FileLength": 2083340, "HasInstallScript": false, "Id": 2304146, "InstallMetadata": null, "Modules": [{"Foldername": "META-INF", "Fingerprint": 987865041}, {"Foldername": "slimeknights", "Fingerprint": 348905915}, {"Foldername": "pack.mcmeta", "Fingerprint": 219889385}, {"Foldername": "mcmod.info", "Fingerprint": 4159749293}, {"Foldername": "TinkersConstruct.png", "Fingerprint": 3056415901}, {"Foldername": "logo.png", "Fingerprint": 3056415901}, {"Foldername": "assets", "Fingerprint": 1371493239}], "GameVersionDateReleased": "2007-07-01T05:00:00Z", "__comment": "Deprecated! [Served by AWS Lambda]", "AlternateFileId": 0, "FileName": "TConstruct-1.9.4-2.3.1.jenkins229.jar", "GameVersion": ["1.9.4"], "ReleaseType": 3, "DisplayName": "TConstruct-1.9.4-2.3.1.jenkins229.jar", "PackageFingerprint": 2049031408, "_Project": {"PackageType": "Mod", "Path": "mods"}, "IsAlternate": false, "FileDate": "2016-05-31T19:18:32.793Z", "ServerPackFileId": null, "IsAvailable": true, "GameVersionFlavor": null, "DownloadURL": "https://edge.forgecdn.net/files/2304/146/TConstruct-1.9.4-2.3.1.jenkins229.jar", "FileStatus": 4, "FileNameOnDisk": "TConstruct-1.9.4-2.3.1.jenkins229.jar"}