{"Dependencies": [], "FileLength": 393358, "HasInstallScript": false, "Id": 2316784, "InstallMetadata": null, "Modules": [{"Foldername": "META-INF", "Fingerprint": 2464251221}, {"Foldername": "dk", "Fingerprint": 3671385487}, {"Foldername": "mcmod.info", "Fingerprint": 3638920200}, {"Foldername": "assets", "Fingerprint": 3312996598}], "GameVersionDateReleased": "2014-06-16T00:00:00Z", "__comment": "Deprecated! [Served by AWS Lambda]", "AlternateFileId": 2316786, "FileName": "TheKitchenMod-1.3.20-1.7.2-10.jar", "GameVersion": ["1.7.10"], "ReleaseType": 1, "DisplayName": "v1.3.20-1.7.10", "PackageFingerprint": 325509615, "_Project": {"PackageType": "Mod", "Path": "mods"}, "IsAlternate": false, "FileDate": "2016-07-17T23:02:55.763Z", "ServerPackFileId": null, "IsAvailable": true, "GameVersionFlavor": null, "DownloadURL": "https://edge.forgecdn.net/files/2316/784/TheKitchenMod-1.3.20-1.7.2-10.jar", "FileStatus": 4, "FileNameOnDisk": "TheKitchenMod-1.3.20-1.7.2-10.jar"}