{"Dependencies": [], "FileLength": 262408, "HasInstallScript": false, "Id": 2322265, "InstallMetadata": null, "Modules": [{"Foldername": "META-INF", "Fingerprint": 2464251221}, {"Foldername": "feyberryjam", "Fingerprint": 4186900145}, {"Foldername": "net", "Fingerprint": 2874051388}, {"Foldername": "mcmod.info", "Fingerprint": 1086535557}, {"Foldername": "assets", "Fingerprint": 1754920779}], "GameVersionDateReleased": "2016-05-10T05:00:00Z", "__comment": "Deprecated! [Served by AWS Lambda]", "AlternateFileId": 0, "FileName": "druidry(2016.8.10.2)(1.9.9).jar", "GameVersion": ["1.9.4", "1.10.2", "1.10.1", "1.10"], "ReleaseType": 2, "DisplayName": "Druidry v2016.8.10.2 for MC 1.9.4 to 1.10.2", "PackageFingerprint": 433622870, "_Project": {"PackageType": "Mod", "Path": "mods"}, "IsAlternate": false, "FileDate": "2016-08-11T00:31:10.46Z", "ServerPackFileId": null, "IsAvailable": true, "GameVersionFlavor": null, "DownloadURL": "https://edge.forgecdn.net/files/2322/265/druidry(2016.8.10.2)(1.9.9).jar", "FileStatus": 4, "FileNameOnDisk": "druidry(2016.8.10.2)(1.9.9).jar"}