{"Dependencies": [], "FileLength": 517895, "HasInstallScript": false, "Id": 2326267, "InstallMetadata": null, "Modules": [{"Foldername": "manifest.json", "Fingerprint": 1820135058}], "GameVersionDateReleased": "2016-06-23T05:00:00Z", "__comment": "Deprecated! [Served by AWS Lambda]", "AlternateFileId": 0, "FileName": "Star(Fall)Craft-1.7a.zip", "GameVersion": ["1.10.2"], "ReleaseType": 1, "DisplayName": "Star(Fall)Craft-1.7a.zip", "PackageFingerprint": 2887009300, "_Project": {"PackageType": "ModPack", "Path": "downloads"}, "IsAlternate": false, "FileDate": "2016-08-25T23:32:47.447Z", "ServerPackFileId": null, "IsAvailable": true, "GameVersionFlavor": null, "DownloadURL": "https://edge.forgecdn.net/files/2326/267/Star(Fall)Craft-1.7a.zip", "FileStatus": 4, "FileNameOnDisk": "Star(Fall)Craft-1.7a.zip"}