{"Dependencies": [{"Type": 3, "AddonId": 242818}], "FileLength": 653684, "HasInstallScript": false, "Id": 2377587, "InstallMetadata": null, "Modules": [{"Foldername": "META-INF", "Fingerprint": 3893027612}, {"Foldername": "mrtjp", "Fingerprint": 764467942}, {"Foldername": "assets", "Fingerprint": 963349118}, {"Foldername": "mcmod.info", "Fingerprint": 139762352}, {"Foldername": "Changelog", "Fingerprint": 513525721}], "GameVersionDateReleased": "2016-06-23T05:00:00Z", "__comment": "Deprecated! [Served by AWS Lambda]", "AlternateFileId": 0, "FileName": "MrTJPCore-1.10.2-2.0.0.12-universal.jar", "GameVersion": ["1.10.2"], "ReleaseType": 1, "DisplayName": "MrTJPCore-1.10.2-2.0.0.12-universal.jar", "PackageFingerprint": 149046594, "_Project": {"PackageType": "Mod", "Path": "mods"}, "IsAlternate": false, "FileDate": "2017-02-04T02:58:18.813Z", "ServerPackFileId": null, "IsAvailable": true, "GameVersionFlavor": null, "DownloadURL": "https://edge.forgecdn.net/files/2377/587/MrTJPCore-1.10.2-2.0.0.12-universal.jar", "FileStatus": 4, "FileNameOnDisk": "MrTJPCore-1.10.2-2.0.0.12-universal.jar"}