{"Dependencies": [{"Type": 3, "AddonId": 69162}, {"Type": 3, "AddonId": 222880}, {"Type": 3, "AddonId": 242818}], "FileLength": 1622748, "HasInstallScript": false, "Id": 2388879, "InstallMetadata": null, "Modules": [{"Foldername": "META-INF", "Fingerprint": 2590625257}, {"Foldername": "cofh", "Fingerprint": 2928542691}, {"Foldername": "mcmod.info", "Fingerprint": 2430839359}, {"Foldername": "assets", "Fingerprint": 265804905}], "GameVersionDateReleased": "2016-06-23T05:00:00Z", "__comment": "Deprecated! [Served by AWS Lambda]", "AlternateFileId": 0, "FileName": "ThermalExpansion-1.10.2-2.0.0.64-universal.jar", "GameVersion": ["1.10.2"], "ReleaseType": 2, "DisplayName": "ThermalExpansion-1.10.2-2.0.0.64-universal.jar", "PackageFingerprint": 1403484409, "_Project": {"PackageType": "Mod", "Path": "mods"}, "IsAlternate": false, "FileDate": "2017-03-04T23:55:26.19Z", "ServerPackFileId": null, "IsAvailable": false, "GameVersionFlavor": null, "DownloadURL": "https://edge.forgecdn.net/files/2388/879/ThermalExpansion-1.10.2-2.0.0.64-universal.jar", "FileStatus": 8, "FileNameOnDisk": "ThermalExpansion-1.10.2-2.0.0.64-universal.jar"}