{"Dependencies": [{"Type": 3, "AddonId": 237903}], "FileLength": 1968934, "HasInstallScript": false, "Id": 2393047, "InstallMetadata": null, "Modules": [{"Foldername": "META-INF", "Fingerprint": 1385922743}, {"Foldername": "techreborn", "Fingerprint": 265807418}, {"Foldername": "mcmod.info", "Fingerprint": 1913568942}, {"Foldername": "pack.mcmeta", "Fingerprint": 2361099824}, {"Foldername": "assets", "Fingerprint": 3135311142}], "GameVersionDateReleased": "2016-06-23T05:00:00Z", "__comment": "Deprecated! [Served by AWS Lambda]", "AlternateFileId": 2393048, "FileName": "TechReborn-1.10.2-2.1.10.201-universal.jar", "GameVersion": ["1.10.2"], "ReleaseType": 1, "DisplayName": "TechReborn-1.10.2-2.1.10.201-universal.jar", "PackageFingerprint": 1731919367, "_Project": {"PackageType": "Mod", "Path": "mods"}, "IsAlternate": false, "FileDate": "2017-03-14T13:36:47.253Z", "ServerPackFileId": null, "IsAvailable": true, "GameVersionFlavor": null, "DownloadURL": "https://edge.forgecdn.net/files/2393/47/TechReborn-1.10.2-2.1.10.201-universal.jar", "FileStatus": 4, "FileNameOnDisk": "TechReborn-1.10.2-2.1.10.201-universal.jar"}