{"Dependencies": [], "FileLength": 45599, "HasInstallScript": false, "Id": 2450380, "InstallMetadata": null, "Modules": [{"Foldername": "META-INF", "Fingerprint": 2464251221}, {"Foldername": "net", "Fingerprint": 3520847380}, {"Foldername": "mcmod.info", "Fingerprint": 714648074}, {"Foldername": "README.txt", "Fingerprint": 2876538170}, {"Foldername": "assets", "Fingerprint": 3070615545}], "GameVersionDateReleased": "2016-12-21T06:00:00Z", "__comment": "Deprecated! [Served by AWS Lambda]", "AlternateFileId": 0, "FileName": "hopperducts-mc1.11.2-1.4.9.2.jar", "GameVersion": ["1.11.2"], "ReleaseType": 1, "DisplayName": "Hopper Ducts v1.4.9.2 (for Minecraft 1.11.2)", "PackageFingerprint": 3786156493, "_Project": {"PackageType": "Mod", "Path": "mods"}, "IsAlternate": false, "FileDate": "2017-07-14T02:36:05.283Z", "ServerPackFileId": null, "IsAvailable": true, "GameVersionFlavor": null, "DownloadURL": "https://edge.forgecdn.net/files/2450/380/hopperducts-mc1.11.2-1.4.9.2.jar", "FileStatus": 4, "FileNameOnDisk": "hopperducts-mc1.11.2-1.4.9.2.jar"}