{"Dependencies": [], "FileLength": 12766, "HasInstallScript": false, "Id": 2453940, "InstallMetadata": null, "Modules": [{"Foldername": "META-INF", "Fingerprint": 2464251221}, {"Foldername": "io", "Fingerprint": 3835069164}, {"Foldername": "mcmod.info", "Fingerprint": 1969008393}], "GameVersionDateReleased": "2014-06-16T00:00:00Z", "__comment": "Deprecated! [Served by AWS Lambda]", "AlternateFileId": 0, "FileName": "HitRangeMod-1.2 [1.7.10].jar", "GameVersion": ["1.7.10"], "ReleaseType": 1, "DisplayName": "Hit Range Mod 1.2 [1.7.10]", "PackageFingerprint": 1881401159, "_Project": {"PackageType": "Mod", "Path": "mods"}, "IsAlternate": false, "FileDate": "2017-07-21T12:48:24.757Z", "ServerPackFileId": null, "IsAvailable": true, "GameVersionFlavor": null, "DownloadURL": "https://edge.forgecdn.net/files/2453/940/HitRangeMod-1.2 [1.7.10].jar", "FileStatus": 4, "FileNameOnDisk": "HitRangeMod-1.2 [1.7.10].jar"}