{"Dependencies": [], "FileLength": 53475, "HasInstallScript": false, "Id": 2459089, "InstallMetadata": null, "Modules": [{"Foldername": "META-INF", "Fingerprint": 2464251221}, {"Foldername": "clayborn", "Fingerprint": 204505872}, {"Foldername": "assets", "Fingerprint": 4109098812}, {"Foldername": "mcmod.info", "Fingerprint": 1770738705}, {"Foldername": "pack.mcmeta", "Fingerprint": 3019628261}], "GameVersionDateReleased": "2008-03-01T06:00:00Z", "__comment": "Deprecated! [Served by AWS Lambda]", "AlternateFileId": 0, "FileName": "universalremote-0.66.jar", "GameVersion": ["1.12"], "ReleaseType": 2, "DisplayName": "universalremote-0.66.jar", "PackageFingerprint": 2908758800, "_Project": {"PackageType": "Mod", "Path": "mods"}, "IsAlternate": false, "FileDate": "2017-08-02T07:37:45.19Z", "ServerPackFileId": null, "IsAvailable": true, "GameVersionFlavor": null, "DownloadURL": "https://edge.forgecdn.net/files/2459/89/universalremote-0.66.jar", "FileStatus": 4, "FileNameOnDisk": "universalremote-0.66.jar"}