{"Dependencies": [{"Type": 3, "AddonId": 265894}], "FileLength": 55995, "HasInstallScript": false, "Id": 2486112, "InstallMetadata": null, "Modules": [{"Foldername": "assets", "Fingerprint": 38777384}, {"Foldername": "com", "Fingerprint": 935498361}, {"Foldername": "mcmod.info", "Fingerprint": 2615544410}, {"Foldername": "META-INF", "Fingerprint": 2464251221}, {"Foldername": "OTGlogo.png", "Fingerprint": 619918241}], "GameVersionDateReleased": "2017-09-18T05:00:00Z", "__comment": "Deprecated! [Served by AWS Lambda]", "AlternateFileId": 0, "FileName": "OTG-Flatlands-1.12.2-v4.jar", "GameVersion": ["1.12.2"], "ReleaseType": 1, "DisplayName": "OTG-Flatlands-1.12.2-v4", "PackageFingerprint": 1825161159, "_Project": {"PackageType": "Mod", "Path": "mods"}, "IsAlternate": false, "FileDate": "2017-10-01T09:43:32.183Z", "ServerPackFileId": null, "IsAvailable": true, "GameVersionFlavor": null, "DownloadURL": "https://edge.forgecdn.net/files/2486/112/OTG-Flatlands-1.12.2-v4.jar", "FileStatus": 4, "FileNameOnDisk": "OTG-Flatlands-1.12.2-v4.jar"}