{"PackageFingerprint": 3867679025, "DisplayName": "PotionFingers-r1.0-2.jar", "FileLength": 10774, "FileStatus": 4, "ReleaseType": 1, "FileDate": "2017-10-18T11:02:00.09Z", "FileNameOnDisk": "PotionFingers-r1.0-2.jar", "Dependencies": [{"Type": 3, "AddonId": 227083}, {"Type": 3, "AddonId": 250363}], "IsAlternate": false, "GameVersion": ["1.12", "1.12.1", "1.12.2"], "FileName": "PotionFingers-r1.0-2.jar", "ServerPackFileId": null, "IsAvailable": true, "__comment": "Deprecated! [Served by AWS Lambda]", "GameVersionFlavor": null, "AlternateFileId": 0, "Id": 2491881, "InstallMetadata": null, "Modules": [{"Foldername": "META-INF", "Fingerprint": 2464251221}, {"Foldername": "vazkii", "Fingerprint": 2373553943}, {"Foldername": "mcmod.info", "Fingerprint": 1289114851}, {"Foldername": "assets", "Fingerprint": 3067133661}], "_Project": {"Path": "mods", "PackageType": "Mod"}, "GameVersionDateReleased": "2008-03-01T06:00:00Z", "HasInstallScript": false, "DownloadURL": "https://edge.forgecdn.net/files/2491/881/PotionFingers-r1.0-2.jar"}