{"Dependencies": [], "FileLength": 402774, "HasInstallScript": false, "Id": 2497541, "InstallMetadata": null, "Modules": [{"Foldername": "META-INF", "Fingerprint": 2464251221}, {"Foldername": "api", "Fingerprint": 2801823682}, {"Foldername": "climateControl", "Fingerprint": 1582245004}, {"Foldername": "com", "Fingerprint": 2131782996}, {"Foldername": "mcmod.info", "Fingerprint": 192310991}], "GameVersionDateReleased": "2008-03-01T06:00:00Z", "__comment": "Deprecated! [Served by AWS Lambda]", "AlternateFileId": 0, "FileName": "GeographiCraft-1.12-0.8.9b.jar", "GameVersion": ["1.12", "1.12.1", "1.12.2"], "ReleaseType": 1, "DisplayName": "GeographiCraft-1.12-0.8.9b.jar", "PackageFingerprint": 42317994, "_Project": {"PackageType": "Mod", "Path": "mods"}, "IsAlternate": false, "FileDate": "2017-11-05T18:36:36.937Z", "ServerPackFileId": null, "IsAvailable": true, "GameVersionFlavor": null, "DownloadURL": "https://edge.forgecdn.net/files/2497/541/GeographiCraft-1.12-0.8.9b.jar", "FileStatus": 4, "FileNameOnDisk": "GeographiCraft-1.12-0.8.9b.jar"}