{"Dependencies": [], "FileLength": 638244, "HasInstallScript": false, "Id": 2509809, "InstallMetadata": null, "Modules": [{"Foldername": "META-INF", "Fingerprint": 3668080586}, {"Foldername": "assets", "Fingerprint": 1868217626}, {"Foldername": "codechicken", "Fingerprint": 2929327102}, {"Foldername": "mcmod.info", "Fingerprint": 2884101261}], "GameVersionDateReleased": "2016-12-21T06:00:00Z", "__comment": "Deprecated! [Served by AWS Lambda]", "AlternateFileId": 2509810, "FileName": "CodeChickenLib-1.11.2-3.0.0.328-universal.jar", "GameVersion": ["1.11.2"], "ReleaseType": 1, "DisplayName": "CodeChicken Lib 1.11.2-3.0.0.328-universal", "PackageFingerprint": 4260533217, "_Project": {"PackageType": "Mod", "Path": "mods"}, "IsAlternate": false, "FileDate": "2017-12-15T02:32:12.453Z", "ServerPackFileId": null, "IsAvailable": true, "GameVersionFlavor": null, "DownloadURL": "https://edge.forgecdn.net/files/2509/809/CodeChickenLib-1.11.2-3.0.0.328-universal.jar", "FileStatus": 4, "FileNameOnDisk": "CodeChickenLib-1.11.2-3.0.0.328-universal.jar"}