{"Dependencies": [], "FileLength": 986664, "HasInstallScript": false, "Id": 2523730, "InstallMetadata": null, "Modules": [{"Foldername": "META-INF", "Fingerprint": 2464251221}, {"Foldername": "com", "Fingerprint": 2253854285}, {"Foldername": "assets", "Fingerprint": 661143683}, {"Foldername": "changelog.txt", "Fingerprint": 974627760}, {"Foldername": "mcmod.info", "Fingerprint": 2038421807}, {"Foldername": "pack.mcmeta", "Fingerprint": 666645652}], "GameVersionDateReleased": "2017-09-18T05:00:00Z", "__comment": "Deprecated! [Served by AWS Lambda]", "AlternateFileId": 0, "FileName": "MikeDongles-0.6.0-[1.12.2].jar", "GameVersion": ["1.12.2"], "ReleaseType": 1, "DisplayName": "MikeDongles 0.6.0 [1.12.2]", "PackageFingerprint": 1304177175, "_Project": {"PackageType": "Mod", "Path": "mods"}, "IsAlternate": false, "FileDate": "2018-01-24T16:34:02.457Z", "ServerPackFileId": null, "IsAvailable": true, "GameVersionFlavor": null, "DownloadURL": "https://edge.forgecdn.net/files/2523/730/MikeDongles-0.6.0-[1.12.2].jar", "FileStatus": 4, "FileNameOnDisk": "MikeDongles-0.6.0-[1.12.2].jar"}