{"Dependencies": [{"Type": 3, "AddonId": 74924}], "FileLength": 3760118, "HasInstallScript": false, "Id": 2530200, "InstallMetadata": null, "Modules": [{"Foldername": "META-INF", "Fingerprint": 149252737}, {"Foldername": "slimeknights", "Fingerprint": 3575992920}, {"Foldername": "assets", "Fingerprint": 116548058}, {"Foldername": "pack.mcmeta", "Fingerprint": 219889385}, {"Foldername": "mcmod.info", "Fingerprint": 1768600264}, {"Foldername": "logo.png", "Fingerprint": 3056415901}], "GameVersionDateReleased": "2008-03-01T06:00:00Z", "__comment": "Deprecated! [Served by AWS Lambda]", "AlternateFileId": 0, "FileName": "TConstruct-1.12.2-2.9.1.65.jar", "GameVersion": ["1.12.2"], "ReleaseType": 1, "DisplayName": "TConstruct-1.12.2-2.9.1.65.jar", "PackageFingerprint": 2308260770, "_Project": {"PackageType": "Mod", "Path": "mods"}, "IsAlternate": false, "FileDate": "2018-02-11T12:58:05.54Z", "ServerPackFileId": null, "IsAvailable": true, "GameVersionFlavor": null, "DownloadURL": "https://edge.forgecdn.net/files/2530/200/TConstruct-1.12.2-2.9.1.65.jar", "FileStatus": 4, "FileNameOnDisk": "TConstruct-1.12.2-2.9.1.65.jar"}