{"PackageFingerprint": 3524181929, "DisplayName": "ElevatorMod-1.12.2-1.3.6.jar", "FileLength": 98152, "FileStatus": 4, "ReleaseType": 1, "FileDate": "2018-03-13T16:23:57.513Z", "FileNameOnDisk": "ElevatorMod-1.12.2-1.3.6.jar", "Dependencies": [], "IsAlternate": false, "GameVersion": ["1.12.2"], "FileName": "ElevatorMod-1.12.2-1.3.6.jar", "ServerPackFileId": null, "IsAvailable": true, "__comment": "Deprecated! [Served by AWS Lambda]", "GameVersionFlavor": null, "AlternateFileId": 0, "Id": 2540767, "InstallMetadata": null, "Modules": [{"Foldername": "META-INF", "Fingerprint": 1435464107}, {"Foldername": "xyz", "Fingerprint": 2794633121}, {"Foldername": "assets", "Fingerprint": 671292752}, {"Foldername": "mcmod.info", "Fingerprint": 1640870774}], "_Project": {"Path": "mods", "PackageType": "Mod"}, "GameVersionDateReleased": "2017-09-18T05:00:00Z", "HasInstallScript": false, "DownloadURL": "https://edge.forgecdn.net/files/2540/767/ElevatorMod-1.12.2-1.3.6.jar"}