{"Dependencies": [{"Type": 2, "AddonId": 283447}, {"Type": 2, "AddonId": 224472}, {"Type": 2, "AddonId": 267602}], "FileLength": 6694138, "HasInstallScript": false, "Id": 2547347, "InstallMetadata": null, "Modules": [{"Foldername": "META-INF", "Fingerprint": 2641849666}, {"Foldername": "betterwithmods", "Fingerprint": 1027855916}, {"Foldername": "proxypack.mcmeta", "Fingerprint": 2525296592}, {"Foldername": "mcmod.info", "Fingerprint": 2752693207}, {"Foldername": "assets", "Fingerprint": 3950179056}], "GameVersionDateReleased": "2017-06-07T05:00:00Z", "__comment": "Deprecated! [Served by AWS Lambda]", "AlternateFileId": 0, "FileName": "BetterWithMods-1.12-2.0.34.jar", "GameVersion": ["1.12", "1.12.1", "1.12.2"], "ReleaseType": 1, "DisplayName": "BetterWithMods-1.12-2.0.34.jar", "PackageFingerprint": 26842923, "_Project": {"PackageType": "Mod", "Path": "mods"}, "IsAlternate": false, "FileDate": "2018-04-01T13:30:01.807Z", "ServerPackFileId": null, "IsAvailable": true, "GameVersionFlavor": null, "DownloadURL": "https://edge.forgecdn.net/files/2547/347/BetterWithMods-1.12-2.0.34.jar", "FileStatus": 4, "FileNameOnDisk": "BetterWithMods-1.12-2.0.34.jar"}