{"Dependencies": [], "FileLength": 58216, "HasInstallScript": false, "Id": 2553148, "InstallMetadata": null, "Modules": [{"Foldername": "META-INF", "Fingerprint": 2864680323}, {"Foldername": "quaternary", "Fingerprint": 2762308528}, {"Foldername": "assets", "Fingerprint": 3029415902}, {"Foldername": "mcmod.info", "Fingerprint": 3666970268}, {"Foldername": "pack.mcmeta", "Fingerprint": 3273911401}], "GameVersionDateReleased": "2017-09-18T05:00:00Z", "__comment": "Deprecated! [Served by AWS Lambda]", "AlternateFileId": 0, "FileName": "breadcrumbtrail-1.1.jar", "GameVersion": ["1.12.2"], "ReleaseType": 1, "DisplayName": "breadcrumbtrail-1.1.jar", "PackageFingerprint": 1968017955, "_Project": {"PackageType": "Mod", "Path": "mods"}, "IsAlternate": false, "FileDate": "2018-04-19T03:50:44.98Z", "ServerPackFileId": null, "IsAvailable": true, "GameVersionFlavor": null, "DownloadURL": "https://edge.forgecdn.net/files/2553/148/breadcrumbtrail-1.1.jar", "FileStatus": 4, "FileNameOnDisk": "breadcrumbtrail-1.1.jar"}