{"Dependencies": [], "FileLength": 79970344, "HasInstallScript": false, "Id": 2577377, "InstallMetadata": null, "Modules": [{"Foldername": "META-INF", "Fingerprint": 1005258150}, {"Foldername": "TheBetweenlands-3.3.10-core.jar", "Fingerprint": 244341475}, {"Foldername": "assets", "Fingerprint": 2754145714}, {"Foldername": "mcmod.info", "Fingerprint": 823952803}, {"Foldername": "thebetweenlands", "Fingerprint": 261971311}], "GameVersionDateReleased": "2008-03-01T06:00:00Z", "__comment": "Deprecated! [Served by AWS Lambda]", "AlternateFileId": 2577378, "FileName": "TheBetweenlands-3.3.10-universal.jar", "GameVersion": ["1.12.2"], "ReleaseType": 1, "DisplayName": "The Betweenlands v3.3.10", "PackageFingerprint": 1971650585, "_Project": {"PackageType": "Mod", "Path": "mods"}, "IsAlternate": false, "FileDate": "2018-06-28T16:25:42.677Z", "ServerPackFileId": null, "IsAvailable": true, "GameVersionFlavor": null, "DownloadURL": "https://edge.forgecdn.net/files/2577/377/TheBetweenlands-3.3.10-universal.jar", "FileStatus": 4, "FileNameOnDisk": "TheBetweenlands-3.3.10-universal.jar"}