{"PackageFingerprint": 3390059214, "DisplayName": "UniDict-1.12.2-2.6.jar", "FileLength": 176686, "FileStatus": 4, "ReleaseType": 1, "FileDate": "2018-08-08T21:24:13.94Z", "FileNameOnDisk": "UniDict-1.12.2-2.6.jar", "Dependencies": [{"Type": 3, "AddonId": 253043}, {"Type": 2, "AddonId": 277047}, {"Type": 2, "AddonId": 239197}], "IsAlternate": false, "GameVersion": ["1.12.2"], "FileName": "UniDict-1.12.2-2.6.jar", "ServerPackFileId": null, "IsAvailable": true, "__comment": "Deprecated! [Served by AWS Lambda]", "GameVersionFlavor": null, "AlternateFileId": 2600130, "Id": 2600127, "InstallMetadata": null, "Modules": [{"Foldername": "META-INF", "Fingerprint": 1379565665}, {"Foldername": "wanion", "Fingerprint": 3686371879}, {"Foldername": "mcmod.info", "Fingerprint": 2631394295}, {"Foldername": "pack.mcmeta", "Fingerprint": 2081512886}, {"Foldername": "unidictlogo.png", "Fingerprint": 3434512620}], "_Project": {"Path": "mods", "PackageType": "Mod"}, "GameVersionDateReleased": "2008-03-01T06:00:00Z", "HasInstallScript": false, "DownloadURL": "https://edge.forgecdn.net/files/2600/127/UniDict-1.12.2-2.6.jar"}