{"Dependencies": [{"Type": 2, "AddonId": 223815}], "FileLength": 1819663, "HasInstallScript": false, "Id": 2608872, "InstallMetadata": null, "Modules": [{"Foldername": "META-INF", "Fingerprint": 966961602}, {"Foldername": "com", "Fingerprint": 662608016}, {"Foldername": "mcmod.info", "Fingerprint": 3735463412}, {"Foldername": "assets", "Fingerprint": 3581336925}], "GameVersionDateReleased": "2017-09-18T05:00:00Z", "__comment": "Deprecated! [Served by AWS Lambda]", "AlternateFileId": 0, "FileName": "Signals-1.12.2-1.3.12-23-universal.jar", "GameVersion": ["1.12.2"], "ReleaseType": 1, "DisplayName": "Signals-1.12.2-1.3.12-23-universal.jar", "PackageFingerprint": 1848558526, "_Project": {"PackageType": "Mod", "Path": "mods"}, "IsAlternate": false, "FileDate": "2018-08-26T16:31:20.293Z", "ServerPackFileId": null, "IsAvailable": true, "GameVersionFlavor": null, "DownloadURL": "https://edge.forgecdn.net/files/2608/872/Signals-1.12.2-1.3.12-23-universal.jar", "FileStatus": 4, "FileNameOnDisk": "Signals-1.12.2-1.3.12-23-universal.jar"}