{"Dependencies": [], "FileLength": 93642654, "HasInstallScript": false, "Id": 2629721, "InstallMetadata": null, "Modules": [{"Foldername": "manifest.json", "Fingerprint": 3971789401}], "GameVersionDateReleased": "2014-06-16T00:00:00Z", "__comment": "Deprecated! [Served by AWS Lambda]", "AlternateFileId": 0, "FileName": "DivineWorld-2.0.zip", "GameVersion": ["1.7.10"], "ReleaseType": 2, "DisplayName": "DivineWorld", "PackageFingerprint": 2968466549, "_Project": {"PackageType": "ModPack", "Path": "downloads"}, "IsAlternate": false, "FileDate": "2018-10-20T07:43:16.827Z", "ServerPackFileId": null, "IsAvailable": true, "GameVersionFlavor": null, "DownloadURL": "https://edge.forgecdn.net/files/2629/721/DivineWorld-2.0.zip", "FileStatus": 4, "FileNameOnDisk": "DivineWorld-2.0.zip"}