{"Dependencies": [{"Type": 3, "AddonId": 268704}], "FileLength": 8983873, "HasInstallScript": false, "Id": 2632921, "InstallMetadata": null, "Modules": [{"Foldername": "META-INF", "Fingerprint": 1332485108}, {"Foldername": "com", "Fingerprint": 1064736981}, {"Foldername": "addons.mcmeta", "Fingerprint": 2673473374}, {"Foldername": "assets", "Fingerprint": 937226640}, {"Foldername": "mcmod.info", "Fingerprint": 130719615}], "GameVersionDateReleased": "2008-03-01T06:00:00Z", "__comment": "Deprecated! [Served by AWS Lambda]", "AlternateFileId": 0, "FileName": "animania-1.12.2-1.6.jar", "GameVersion": ["1.12.2"], "ReleaseType": 1, "DisplayName": " Animania-1.12.2-1.6", "PackageFingerprint": 4157181297, "_Project": {"PackageType": "Mod", "Path": "mods"}, "IsAlternate": false, "FileDate": "2018-10-29T00:05:06.473Z", "ServerPackFileId": null, "IsAvailable": true, "GameVersionFlavor": null, "DownloadURL": "https://edge.forgecdn.net/files/2632/921/animania-1.12.2-1.6.jar", "FileStatus": 4, "FileNameOnDisk": "animania-1.12.2-1.6.jar"}