{"Dependencies": [{"Type": 3, "AddonId": 223794}, {"Type": 3, "AddonId": 223628}], "FileLength": 601016, "HasInstallScript": false, "Id": 2669776, "InstallMetadata": null, "Modules": [{"Foldername": "META-INF", "Fingerprint": 3131272362}, {"Foldername": "thaumicenergistics", "Fingerprint": 3368602439}, {"Foldername": "assets", "Fingerprint": 3108123956}, {"Foldername": "mcmod.info", "Fingerprint": 1859895647}, {"Foldername": "pack.mcmeta", "Fingerprint": 301760938}], "GameVersionDateReleased": "2008-03-01T06:00:00Z", "__comment": "Deprecated! [Served by AWS Lambda]", "AlternateFileId": 2669777, "FileName": "thaumicenergistics-2.1.1.jar", "GameVersion": ["1.12.2"], "ReleaseType": 1, "DisplayName": "(AE2-RV6) Thaumic Energistics 2.1.1", "PackageFingerprint": 777625202, "_Project": {"PackageType": "Mod", "Path": "mods"}, "IsAlternate": false, "FileDate": "2019-02-06T14:25:05.593Z", "ServerPackFileId": null, "IsAvailable": true, "GameVersionFlavor": null, "DownloadURL": "https://edge.forgecdn.net/files/2669/776/thaumicenergistics-2.1.1.jar", "FileStatus": 4, "FileNameOnDisk": "thaumicenergistics-2.1.1.jar"}