{"Dependencies": [], "FileLength": 30952, "HasInstallScript": false, "Id": 2670169, "InstallMetadata": null, "Modules": [{"Foldername": "META-INF", "Fingerprint": 3426554806}, {"Foldername": "brightspark", "Fingerprint": 599228554}, {"Foldername": "assets", "Fingerprint": 3015014052}, {"Foldername": "mcmod.info", "Fingerprint": 4178313169}, {"Foldername": "pack.mcmeta", "Fingerprint": 2678006413}], "GameVersionDateReleased": "2017-09-18T05:00:00Z", "__comment": "Deprecated! [Served by AWS Lambda]", "AlternateFileId": 0, "FileName": "mirageorb-1.12.2-1.1.0.jar", "GameVersion": ["1.12.2"], "ReleaseType": 1, "DisplayName": "mirageorb-1.12.2-1.1.0.jar", "PackageFingerprint": 1243775356, "_Project": {"PackageType": "Mod", "Path": "mods"}, "IsAlternate": false, "FileDate": "2019-02-07T12:24:31.797Z", "ServerPackFileId": null, "IsAvailable": true, "GameVersionFlavor": null, "DownloadURL": "https://edge.forgecdn.net/files/2670/169/mirageorb-1.12.2-1.1.0.jar", "FileStatus": 4, "FileNameOnDisk": "mirageorb-1.12.2-1.1.0.jar"}