{"Dependencies": [{"Type": 3, "AddonId": 223628}, {"Type": 3, "AddonId": 256141}], "FileLength": 594111, "HasInstallScript": false, "Id": 2670641, "InstallMetadata": null, "Modules": [{"Foldername": "META-INF", "Fingerprint": 1877157292}, {"Foldername": "com", "Fingerprint": 2641836225}, {"Foldername": "assets", "Fingerprint": 773043195}, {"Foldername": "mcmod.info", "Fingerprint": 2361480697}, {"Foldername": "pack.mcmeta", "Fingerprint": 3273911401}, {"Foldername": "rusticthaumaturgy_at.cfg", "Fingerprint": 842978913}], "GameVersionDateReleased": "2008-03-01T06:00:00Z", "__comment": "Deprecated! [Served by AWS Lambda]", "AlternateFileId": 0, "FileName": "Rustic Thaumaturgy-4.1.jar", "GameVersion": ["1.12.2"], "ReleaseType": 1, "DisplayName": "Rustic Thaumaturgy v4.1", "PackageFingerprint": 1152075081, "_Project": {"PackageType": "Mod", "Path": "mods"}, "IsAlternate": false, "FileDate": "2019-02-08T16:41:12.64Z", "ServerPackFileId": null, "IsAvailable": true, "GameVersionFlavor": null, "DownloadURL": "https://edge.forgecdn.net/files/2670/641/Rustic Thaumaturgy-4.1.jar", "FileStatus": 4, "FileNameOnDisk": "Rustic Thaumaturgy-4.1.jar"}