{"Dependencies": [], "FileLength": 2349729, "HasInstallScript": false, "Id": 2674947, "InstallMetadata": null, "Modules": [{"Foldername": "META-INF", "Fingerprint": 4102595494}, {"Foldername": "de", "Fingerprint": 3234125918}, {"Foldername": "com", "Fingerprint": 498821832}, {"Foldername": "darwin", "Fingerprint": 1811848468}, {"Foldername": "linux", "Fingerprint": 35998981}, {"Foldername": "net", "Fingerprint": 3448600313}, {"Foldername": "win-x64", "Fingerprint": 1948685191}, {"Foldername": "win-x86", "Fingerprint": 1714382561}, {"Foldername": "fr", "Fingerprint": 2128558771}], "GameVersionDateReleased": "2017-06-07T05:00:00Z", "__comment": "Deprecated! [Served by AWS Lambda]", "AlternateFileId": 0, "FileName": "discordrpc-1.2.2.jar", "GameVersion": ["1.12", "1.12.1", "1.12.2"], "ReleaseType": 1, "DisplayName": "discordrpc-1.2.2.jar", "PackageFingerprint": 3834295255, "_Project": {"PackageType": "Mod", "Path": "mods"}, "IsAlternate": false, "FileDate": "2019-02-15T20:11:20.413Z", "ServerPackFileId": null, "IsAvailable": true, "GameVersionFlavor": null, "DownloadURL": "https://edge.forgecdn.net/files/2674/947/discordrpc-1.2.2.jar", "FileStatus": 4, "FileNameOnDisk": "discordrpc-1.2.2.jar"}