{"Dependencies": [{"Type": 3, "AddonId": 220318}], "FileLength": 140229, "HasInstallScript": false, "Id": 2677434, "InstallMetadata": null, "Modules": [{"Foldername": "META-INF", "Fingerprint": 1219724588}, {"Foldername": "DelirusCrux", "Fingerprint": 3468880646}, {"Foldername": "assets", "Fingerprint": 1225709025}, {"Foldername": "mcmod.info", "Fingerprint": 1714136391}], "GameVersionDateReleased": "2017-09-18T05:00:00Z", "__comment": "Deprecated! [Served by AWS Lambda]", "AlternateFileId": 0, "FileName": "ATOP-1.12.2-v.1.5.jar", "GameVersion": ["1.12.2"], "ReleaseType": 1, "DisplayName": "ATOP-1.12.2-v.1.5.jar", "PackageFingerprint": 1158740505, "_Project": {"PackageType": "Mod", "Path": "mods"}, "IsAlternate": false, "FileDate": "2019-02-20T12:47:58.53Z", "ServerPackFileId": null, "IsAvailable": true, "GameVersionFlavor": null, "DownloadURL": "https://edge.forgecdn.net/files/2677/434/ATOP-1.12.2-v.1.5.jar", "FileStatus": 4, "FileNameOnDisk": "ATOP-1.12.2-v.1.5.jar"}