{"PackageFingerprint": 3885125123, "DisplayName": "MainMenuScale-1.3.2.jar", "FileLength": 4174, "FileStatus": 4, "ReleaseType": 1, "FileDate": "2019-03-04T18:35:45.483Z", "FileNameOnDisk": "MainMenuScale-1.3.2.jar", "Dependencies": [{"Type": 3, "AddonId": 237903}], "IsAlternate": false, "GameVersion": ["1.12.2"], "FileName": "MainMenuScale-1.3.2.jar", "ServerPackFileId": null, "IsAvailable": true, "__comment": "Deprecated! [Served by AWS Lambda]", "GameVersionFlavor": null, "AlternateFileId": 0, "Id": 2683258, "InstallMetadata": null, "Modules": [{"Foldername": "META-INF", "Fingerprint": 228963438}, {"Foldername": "me", "Fingerprint": 2398838928}], "_Project": {"Path": "mods", "PackageType": "Mod"}, "GameVersionDateReleased": "2017-09-18T05:00:00Z", "HasInstallScript": false, "DownloadURL": "https://edge.forgecdn.net/files/2683/258/MainMenuScale-1.3.2.jar"}