{"Dependencies": [{"Type": 3, "AddonId": 224535}], "FileLength": 7076825, "HasInstallScript": false, "Id": 2688609, "InstallMetadata": null, "Modules": [{"Foldername": "META-INF", "Fingerprint": 1939116997}, {"Foldername": "ivorius", "Fingerprint": 1749076558}, {"Foldername": "mcmod.info", "Fingerprint": 4037251601}, {"Foldername": "assets", "Fingerprint": 3890507103}, {"Foldername": "gfx", "Fingerprint": 84000277}, {"Foldername": "dummyThing", "Fingerprint": 79582461}, {"Foldername": "kotlin", "Fingerprint": 1647015965}, {"Foldername": "org", "Fingerprint": 1729624813}], "GameVersionDateReleased": "2008-03-01T06:00:00Z", "__comment": "Deprecated! [Served by AWS Lambda]", "AlternateFileId": 0, "FileName": "RecurrentComplex-1.4.8.1.jar", "GameVersion": ["1.12", "1.12.1", "1.12.2"], "ReleaseType": 1, "DisplayName": "RecurrentComplex-1.4.8.1.jar", "PackageFingerprint": 3396466747, "_Project": {"PackageType": "Mod", "Path": "mods"}, "IsAlternate": false, "FileDate": "2019-03-17T23:09:43.247Z", "ServerPackFileId": null, "IsAvailable": true, "GameVersionFlavor": null, "DownloadURL": "https://edge.forgecdn.net/files/2688/609/RecurrentComplex-1.4.8.1.jar", "FileStatus": 4, "FileNameOnDisk": "RecurrentComplex-1.4.8.1.jar"}