{"Dependencies": [], "FileLength": 3493, "HasInstallScript": false, "Id": 2700031, "InstallMetadata": null, "Modules": [{"Foldername": "META-INF", "Fingerprint": 2464251221}, {"Foldername": "DelirusCrux", "Fingerprint": 1493936489}, {"Foldername": "mcmod.info", "Fingerprint": 3938373414}], "GameVersionDateReleased": "2014-06-16T00:00:00Z", "__comment": "Deprecated! [Served by AWS Lambda]", "AlternateFileId": 0, "FileName": "wild_netherwart-1.7.10-v2.0.jar", "GameVersion": ["1.7.10"], "ReleaseType": 1, "DisplayName": "wild_netherwart-1.7.10-v2.0.jar", "PackageFingerprint": 1262811746, "_Project": {"PackageType": "Mod", "Path": "mods"}, "IsAlternate": false, "FileDate": "2019-04-16T17:26:43.633Z", "ServerPackFileId": null, "IsAvailable": true, "GameVersionFlavor": null, "DownloadURL": "https://edge.forgecdn.net/files/2700/31/wild_netherwart-1.7.10-v2.0.jar", "FileStatus": 4, "FileNameOnDisk": "wild_netherwart-1.7.10-v2.0.jar"}