{"Dependencies": [], "FileLength": 3366219, "HasInstallScript": false, "Id": 2705516, "InstallMetadata": null, "Modules": [{"Foldername": "META-INF", "Fingerprint": 3468327927}, {"Foldername": "me", "Fingerprint": 1939441605}, {"Foldername": "asm", "Fingerprint": 2855666604}, {"Foldername": "assets", "Fingerprint": 2298675060}, {"Foldername": "data", "Fingerprint": 1599323040}, {"Foldername": "pack.mcmeta", "Fingerprint": 312957101}, {"Foldername": "regen_logo.png", "Fingerprint": 1660985600}], "GameVersionDateReleased": "2018-10-22T00:00:00Z", "__comment": "Deprecated! [Served by AWS Lambda]", "AlternateFileId": 0, "FileName": "[1.13.2] Regeneration-0.0.5.jar", "GameVersion": ["1.13.2"], "ReleaseType": 3, "DisplayName": "[ALPHA] This version has been skipped ", "PackageFingerprint": 2790273737, "_Project": {"PackageType": "Mod", "Path": "mods"}, "IsAlternate": false, "FileDate": "2019-04-30T10:40:43.94Z", "ServerPackFileId": null, "IsAvailable": true, "GameVersionFlavor": null, "DownloadURL": "https://edge.forgecdn.net/files/2705/516/[1.13.2] Regeneration-0.0.5.jar", "FileStatus": 4, "FileNameOnDisk": "[1.13.2] Regeneration-0.0.5.jar"}