{"PackageFingerprint": 2418729002, "DisplayName": "[1.12.2] AstikorCarts v0.1.2.7", "FileLength": 102399, "FileStatus": 4, "ReleaseType": 1, "FileDate": "2019-05-03T15:54:38.497Z", "FileNameOnDisk": "astikorcarts-1.12.2-0.1.2.7.jar", "Dependencies": [], "IsAlternate": false, "GameVersion": ["1.12.2"], "FileName": "astikorcarts-1.12.2-0.1.2.7.jar", "ServerPackFileId": null, "IsAvailable": true, "__comment": "Deprecated! [Served by AWS Lambda]", "GameVersionFlavor": null, "AlternateFileId": 0, "Id": 2706762, "InstallMetadata": null, "Modules": [{"Foldername": "META-INF", "Fingerprint": 2707528895}, {"Foldername": "de", "Fingerprint": 2904563143}, {"Foldername": "assets", "Fingerprint": 3054217253}, {"Foldername": "mcmod.info", "Fingerprint": 3591477135}, {"Foldername": "pack.mcmeta", "Fingerprint": 670515405}], "_Project": {"Path": "mods", "PackageType": "Mod"}, "GameVersionDateReleased": "2008-03-01T06:00:00Z", "HasInstallScript": false, "DownloadURL": "https://edge.forgecdn.net/files/2706/762/astikorcarts-1.12.2-0.1.2.7.jar"}