{"Dependencies": [], "FileLength": 9420776, "HasInstallScript": false, "Id": 2713399, "InstallMetadata": null, "Modules": [{"Foldername": "META-INF", "Fingerprint": 1542374704}, {"Foldername": "assets", "Fingerprint": 1851068785}, {"Foldername": "com", "Fingerprint": 130389242}, {"Foldername": "logo.png", "Fingerprint": 280066651}, {"Foldername": "mcmod.info", "Fingerprint": 2267217582}, {"Foldername": "pack.mcmeta", "Fingerprint": 132282778}], "GameVersionDateReleased": "2008-03-01T06:00:00Z", "__comment": "Deprecated! [Served by AWS Lambda]", "AlternateFileId": 0, "FileName": "Overloaded-1.12.2-0.0.56.jar", "GameVersion": ["1.12.2"], "ReleaseType": 1, "DisplayName": "Overloaded-1.12.2-0.0.56.jar", "PackageFingerprint": 3828219421, "_Project": {"PackageType": "Mod", "Path": "mods"}, "IsAlternate": false, "FileDate": "2019-05-19T21:17:38.94Z", "ServerPackFileId": null, "IsAvailable": true, "GameVersionFlavor": null, "DownloadURL": "https://edge.forgecdn.net/files/2713/399/Overloaded-1.12.2-0.0.56.jar", "FileStatus": 4, "FileNameOnDisk": "Overloaded-1.12.2-0.0.56.jar"}