{"Dependencies": [], "FileLength": 264114, "HasInstallScript": false, "Id": 2724831, "InstallMetadata": null, "Modules": [{"Foldername": "META-INF", "Fingerprint": 2068147489}, {"Foldername": "com", "Fingerprint": 2131601431}, {"Foldername": "assets", "Fingerprint": 3465860792}, {"Foldername": "icon.png", "Fingerprint": 3637451881}, {"Foldername": "mcmod.info", "Fingerprint": 3822790035}, {"Foldername": "pack.mcmeta", "Fingerprint": 1999644730}], "GameVersionDateReleased": "2008-03-01T06:00:00Z", "__comment": "Deprecated! [Served by AWS Lambda]", "AlternateFileId": 0, "FileName": "hempfarmer-0.0.1.jar", "GameVersion": ["1.12.2"], "ReleaseType": 1, "DisplayName": "HempFarmer 0.0.1", "PackageFingerprint": 3782373137, "_Project": {"PackageType": "Mod", "Path": "mods"}, "IsAlternate": false, "FileDate": "2019-06-15T07:13:30.893Z", "ServerPackFileId": null, "IsAvailable": true, "GameVersionFlavor": null, "DownloadURL": "https://edge.forgecdn.net/files/2724/831/hempfarmer-0.0.1.jar", "FileStatus": 4, "FileNameOnDisk": "hempfarmer-0.0.1.jar"}