{"Dependencies": [{"Type": 3, "AddonId": 227083}], "FileLength": 77157, "HasInstallScript": false, "Id": 2726827, "InstallMetadata": null, "Modules": [{"Foldername": "META-INF", "Fingerprint": 2521470917}, {"Foldername": "xiroc", "Fingerprint": 2394603891}, {"Foldername": "assets", "Fingerprint": 1951296983}], "GameVersionDateReleased": "2008-03-01T06:00:00Z", "__comment": "Deprecated! [Served by AWS Lambda]", "AlternateFileId": 0, "FileName": "Beneficium-1.12.2-0.5.0.jar", "GameVersion": ["1.12.2"], "ReleaseType": 1, "DisplayName": "Beneficium-1.12.2-0.5.0", "PackageFingerprint": 520158445, "_Project": {"PackageType": "Mod", "Path": "mods"}, "IsAlternate": false, "FileDate": "2019-06-19T16:15:54.343Z", "ServerPackFileId": null, "IsAvailable": true, "GameVersionFlavor": null, "DownloadURL": "https://edge.forgecdn.net/files/2726/827/Beneficium-1.12.2-0.5.0.jar", "FileStatus": 4, "FileNameOnDisk": "Beneficium-1.12.2-0.5.0.jar"}