{"Dependencies": [], "FileLength": 2369851, "HasInstallScript": false, "Id": 2743215, "InstallMetadata": null, "Modules": [{"Foldername": "META-INF", "Fingerprint": 3049560434}, {"Foldername": "svenhjol", "Fingerprint": 1797793834}, {"Foldername": "assets", "Fingerprint": 307830801}, {"Foldername": "mcmod.info", "Fingerprint": 2533812700}], "GameVersionDateReleased": "2017-09-18T05:00:00Z", "__comment": "Deprecated! [Served by AWS Lambda]", "AlternateFileId": 0, "FileName": "Charm-1.12.2-1.2.2.jar", "GameVersion": ["1.12.2"], "ReleaseType": 1, "DisplayName": "Charm-1.12.2-1.2.2.jar", "PackageFingerprint": 2310734752, "_Project": {"PackageType": "Mod", "Path": "mods"}, "IsAlternate": false, "FileDate": "2019-07-17T23:05:29.96Z", "ServerPackFileId": null, "IsAvailable": true, "GameVersionFlavor": null, "DownloadURL": "https://edge.forgecdn.net/files/2743/215/Charm-1.12.2-1.2.2.jar", "FileStatus": 4, "FileNameOnDisk": "Charm-1.12.2-1.2.2.jar"}