{"PackageFingerprint": 2403019824, "DisplayName": "LargeFluidTank-12.4.7.jar", "FileLength": 361728, "FileStatus": 4, "ReleaseType": 1, "FileDate": "2019-09-24T17:20:37.867Z", "FileNameOnDisk": "LargeFluidTank-12.4.7.jar", "Dependencies": [], "IsAlternate": false, "GameVersion": ["1.12.2"], "FileName": "LargeFluidTank-12.4.7.jar", "ServerPackFileId": null, "IsAvailable": true, "__comment": "Deprecated! [Served by AWS Lambda]", "GameVersionFlavor": null, "AlternateFileId": 2794072, "Id": 2794071, "InstallMetadata": null, "Modules": [{"Foldername": "META-INF", "Fingerprint": 422253077}, {"Foldername": "assets", "Fingerprint": 2660544138}, {"Foldername": "com", "Fingerprint": 4235440144}, {"Foldername": "mcmod.info", "Fingerprint": 1459581366}, {"Foldername": "pack.mcmeta", "Fingerprint": 3273911401}], "_Project": {"Path": "mods", "PackageType": "Mod"}, "GameVersionDateReleased": "2017-09-18T05:00:00Z", "HasInstallScript": false, "DownloadURL": "https://edge.forgecdn.net/files/2794/71/LargeFluidTank-12.4.7.jar"}