{"Dependencies": [], "FileLength": 14492461, "HasInstallScript": false, "Id": 2800054, "InstallMetadata": null, "Modules": [{"Foldername": "META-INF", "Fingerprint": 234935894}, {"Foldername": "co", "Fingerprint": 2843079597}, {"Foldername": "assets", "Fingerprint": 878235758}, {"Foldername": "data", "Fingerprint": 3989186731}, {"Foldername": "pack.mcmeta", "Fingerprint": 1890846823}], "GameVersionDateReleased": "2019-07-19T00:00:00Z", "__comment": "Deprecated! [Served by AWS Lambda]", "AlternateFileId": 0, "FileName": "stars-1.0.3.jar", "GameVersion": ["1.14.4", "Forge"], "ReleaseType": 1, "DisplayName": "stars-1.0.3.jar", "PackageFingerprint": 168084703, "_Project": {"PackageType": "Mod", "Path": "mods"}, "IsAlternate": false, "FileDate": "2019-10-01T23:37:03.95Z", "ServerPackFileId": null, "IsAvailable": true, "GameVersionFlavor": null, "DownloadURL": "https://edge.forgecdn.net/files/2800/54/stars-1.0.3.jar", "FileStatus": 4, "FileNameOnDisk": "stars-1.0.3.jar"}